dst_deploy-1.0.2.dist-info/METADATA
dst_deploy-1.0.2.dist-info/WHEEL
dst_deploy/__init__.py
dst_deploy/dst.py
dst_deploy/main.py
dst_deploy/settings.py
dst_deploy/steam.py
dst_deploy/utils/__init__.py
dst_deploy/utils/env.py
dst_deploy-1.0.2.dist-info/RECORD
